b1/b11/nrca.sv
`timescale 1ns/1ps
module fullAdder1bit (
    input logic a, b, cin,
    output wire y, cout
);
    assign #1 y = (a ^ b) ^ cin;
    assign #1 cout = (a & b) | (b & cin) | (cin & a);

endmodule

module nrca #(
    parameter xWIDTH = 4 // Removed the trailing semicolon
) (
    input  logic [xWIDTH-1:0] A, B, // 4 bits: [3:0]
    input  logic Cin,
    output wire [xWIDTH-1:0] Y,
    output wire Cout
);

    // 1. The Internal Carry Chain
    // A 4-bit adder has 5 carry points (1 input, 3 internal, 1 output)
    wire [xWIDTH:0] carry;

    // Wire the main Cin to the start of our carry chain
    assign carry[0] = Cin;

    // 2. The Compile-Time Hardware Generator
    genvar i;
    for (i = 0; i < xWIDTH; i=i+1) begin
        // Instantiate the 1-bit adder and connect the ports dynamically
        fullAdder1bit fa (
            .a(A[i]),
            .b(B[i]),
            .cin(carry[i]),     // Input comes from current carry wire
            .y(Y[i]),
            .cout(carry[i+1])   // Output goes to the NEXT carry wire
        );
    end

    // Wire the end of our carry chain to the main Cout
    assign Cout = carry[xWIDTH];

endmodule

b1/b11/tb_nrca.sv
`timescale 1ns/1ps
module tb_nrca;

    // 1. Declare the parameter FIRST
    parameter tWIDTH = 4;

    // 2. Declare signals (Notice the semicolons!)
    logic [tWIDTH-1:0] AA, BB; 
    logic CCin;
    logic [tWIDTH-1:0] YY;
    logic CCout;
    
    // 3. Instantiate module and pass the parameter
    nrca #(.xWIDTH(tWIDTH)) dut (
        .A(AA),
        .B(BB),
        .Cin(CCin),
        .Y(YY),
        .Cout(CCout)
    );

    // 4. Start sim
    initial begin
        // For GTKWave and execution engine
        $dumpfile("dump.vcd");
        $dumpvars(0, tb_nrca);

        $display("Simulation Starting...");

        // TESTCASE 1: Baseline zero
        AA = 4'b0000; BB = 4'b0000; CCin = 0;
        #10; // Wait 10ns

        // TESTCASE 2: The Worst-Case Ripple
        // Adding 1 to 15 forces the carry bit to travel through all 4 adders
        AA = 4'b0001; BB = 4'b1111; CCin = 0;
        #20; // Give it plenty of time to ripple before finishing

        $display("Simulation Completed...");
        $finish; // Added the missing semicolon here too!
    end

endmodule

b1/b11/dump.vcd
$date
	Thu May 14 16:39:46 2026
$end
$version
	Icarus Verilog
$end
$timescale
	1ps
$end
$scope module tb_nrca $end
$var wire 4 ! YY [3:0] $end
$var wire 1 " CCout $end
$var reg 4 # AA [3:0] $end
$var reg 4 $ BB [3:0] $end
$var reg 1 % CCin $end
$scope module dut $end
$var wire 4 & A [3:0] $end
$var wire 4 ' B [3:0] $end
$var wire 1 % Cin $end
$var wire 5 ( carry [4:0] $end
$var wire 4 ) Y [3:0] $end
$var wire 1 " Cout $end
$scope begin genblk1[0] $end
$scope module fa $end
$var wire 1 * a $end
$var wire 1 + b $end
$var wire 1 , cin $end
$var wire 1 - cout $end
$var wire 1 . y $end
$upscope $end
$upscope $end
$scope begin genblk1[1] $end
$scope module fa $end
$var wire 1 / a $end
$var wire 1 0 b $end
$var wire 1 1 cin $end
$var wire 1 2 cout $end
$var wire 1 3 y $end
$upscope $end
$upscope $end
$scope begin genblk1[2] $end
$scope module fa $end
$var wire 1 4 a $end
$var wire 1 5 b $end
$var wire 1 6 cin $end
$var wire 1 7 cout $end
$var wire 1 8 y $end
$upscope $end
$upscope $end
$scope begin genblk1[3] $end
$scope module fa $end
$var wire 1 9 a $end
$var wire 1 : b $end
$var wire 1 ; cin $end
$var wire 1 < cout $end
$var wire 1 = y $end
$upscope $end
$upscope $end
$upscope $end
$upscope $end
$enddefinitions $end
#0
$dumpvars
x=
x<
x;
0:
09
x8
x7
x6
05
04
x3
x2
x1
00
0/
x.
x-
0,
0+
0*
bx )
bx0 (
b0 '
b0 &
0%
b0 $
b0 #
x"
bx !
$end
#1000
01
06
0;
0"
0-
02
07
b0 (
0<
bx0 !
bx0 )
0.
#2000
03
08
b0 !
b0 )
0=
#10000
1+
10
15
1:
1*
b1111 $
b1111 '
b1 #
b1 &
#11000
11
b10 (
1-
13
18
b1110 !
b1110 )
1=
#12000
16
b110 (
12
b1100 !
b1100 )
03
#13000
1;
b1110 (
17
b1000 !
b1000 )
08
#14000
1"
b11110 (
1<
b0 !
b0 )
0=
